pyllm/__init__.py
pyllm/__main__.py
pyllm/api/__init__.py
pyllm/api/image_routes.py
pyllm/api/routes.py
pyllm/cli/__init__.py
pyllm/cli/main.py
pyllm/core/__init__.py
pyllm/core/config.py
pyllm/inference/__init__.py
pyllm/inference/diffusion.py
pyllm/inference/engine.py
pyllm/inference/generator.py
pyllm/inference/inl_legacy.py
pyllm/inference/templates.py
pyllm/inference/tpu_inl_engine.py
pyllm/ui/__init__.py
pyllm/ui/api.py
pyllm/ui/app.py
pyllm/ui/config.py
pyllm/ui/state.py
pyllm/ui/styles.py
pyllm/ui/components/__init__.py
pyllm/ui/components/chat.py
pyllm/ui/components/custom.py
pyllm/ui/components/sidebar.py
pyllm/ui/pages/__init__.py
pyllm_inference-2.0.3.dist-info/METADATA
pyllm_inference-2.0.3.dist-info/WHEEL
pyllm_inference-2.0.3.dist-info/entry_points.txt
pyllm_inference-2.0.3.dist-info/top_level.txt
pyllm_inference-2.0.3.dist-info/RECORD
