Metadata-Version: 2.4
Name: pyllm-inference
Version: 2.0.3
Summary: PyLLM: LLM Inference with Streaming Chat, OpenAI-compatible API, and TPU-INL acceleration
Home-page: https://github.com/Web3-League/pyllm
Author: nano3
Author-email: 
License-Expression: MIT
Project-URL: Homepage, https://github.com/Web3-League/pyllm
Project-URL: Documentation, https://github.com/Web3-League/pyllm#readme
Project-URL: Repository, https://github.com/Web3-League/pyllm
Project-URL: Issues, https://github.com/Web3-League/pyllm/issues
Keywords: llm,inference,streaming,chat,openai,transformers
Classifier: Development Status :: 4 - Beta
Classifier: Environment :: Console
Classifier: Environment :: GPU :: NVIDIA CUDA
Classifier: Framework :: FastAPI
Classifier: Intended Audience :: Developers
Classifier: Intended Audience :: Science/Research
Classifier: Operating System :: OS Independent
Classifier: Programming Language :: Python :: 3
Classifier: Programming Language :: Python :: 3.8
Classifier: Programming Language :: Python :: 3.9
Classifier: Programming Language :: Python :: 3.10
Classifier: Programming Language :: Python :: 3.11
Classifier: Programming Language :: Python :: 3.12
Classifier: Topic :: Scientific/Engineering :: Artificial Intelligence
Requires-Python: >=3.8
Requires-Dist: torch>=2.0.0
Requires-Dist: transformers>=4.30.0
Requires-Dist: safetensors>=0.3.0
Requires-Dist: tokenizers>=0.15.0
Requires-Dist: fastapi>=0.100.0
Requires-Dist: uvicorn>=0.23.0
Requires-Dist: pydantic>=2.0.0
Provides-Extra: ui
Requires-Dist: streamlit>=1.28.0; extra == "ui"
Requires-Dist: streamlit-shadcn-ui>=0.1.0; extra == "ui"
Requires-Dist: requests>=2.31.0; extra == "ui"
Provides-Extra: complexity
Requires-Dist: complexity-model>=0.7.0; extra == "complexity"
Provides-Extra: complexity-deep
Requires-Dist: complexity-deep>=0.4.0; extra == "complexity-deep"
Provides-Extra: diffusion
Requires-Dist: complexity-diffusion>=0.1.0; extra == "diffusion"
Provides-Extra: cuda
Requires-Dist: triton>=2.0.0; extra == "cuda"
Provides-Extra: all
Requires-Dist: complexity-model>=0.7.0; extra == "all"
Requires-Dist: complexity-deep>=0.4.0; extra == "all"
Requires-Dist: complexity-diffusion>=0.1.0; extra == "all"
Requires-Dist: streamlit>=1.28.0; extra == "all"
Requires-Dist: streamlit-shadcn-ui>=0.1.0; extra == "all"
Requires-Dist: requests>=2.31.0; extra == "all"
Provides-Extra: dev
Requires-Dist: pytest>=7.0.0; extra == "dev"
Requires-Dist: black>=23.0.0; extra == "dev"
Dynamic: home-page
Dynamic: requires-python
